tesla_api_sdk-1.0.2.dist-info/licenses/LICENSE
teslafleetmanagementapi/__init__.py
teslafleetmanagementapi/api_helper.py
teslafleetmanagementapi/configuration.py
teslafleetmanagementapi/teslafleetmanagementapi_client.py
teslafleetmanagementapi/controllers/__init__.py
teslafleetmanagementapi/controllers/base_controller.py
teslafleetmanagementapi/controllers/charging_controller.py
teslafleetmanagementapi/controllers/energy_controller.py
teslafleetmanagementapi/controllers/o_auth_authorization_controller.py
teslafleetmanagementapi/controllers/partner_controller.py
teslafleetmanagementapi/controllers/user_controller.py
teslafleetmanagementapi/controllers/vehicle_commands_controller.py
teslafleetmanagementapi/controllers/vehicles_controller.py
teslafleetmanagementapi/exceptions/__init__.py
teslafleetmanagementapi/exceptions/api_exception.py
teslafleetmanagementapi/exceptions/o_auth_provider_exception.py
teslafleetmanagementapi/http/__init__.py
teslafleetmanagementapi/http/api_response.py
teslafleetmanagementapi/http/http_call_back.py
teslafleetmanagementapi/http/http_client_provider.py
teslafleetmanagementapi/http/http_method_enum.py
teslafleetmanagementapi/http/http_request.py
teslafleetmanagementapi/http/http_response.py
teslafleetmanagementapi/http/proxy_settings.py
teslafleetmanagementapi/http/auth/__init__.py
teslafleetmanagementapi/http/auth/bearer_auth.py
teslafleetmanagementapi/http/auth/thirdpartytoken.py
teslafleetmanagementapi/logging/__init__.py
teslafleetmanagementapi/logging/sdk_logger.py
teslafleetmanagementapi/logging/configuration/__init__.py
teslafleetmanagementapi/logging/configuration/api_logging_configuration.py
teslafleetmanagementapi/models/__init__.py
teslafleetmanagementapi/models/actuate_trunk_request.py
teslafleetmanagementapi/models/add_charge_schedule_request.py
teslafleetmanagementapi/models/add_precondition_schedule_request.py
teslafleetmanagementapi/models/adjust_volume_request.py
teslafleetmanagementapi/models/api_1_dx_vehicles_options_response.py
tesla_api_sdk-1.0.2.dist-info/METADATA
tesla_api_sdk-1.0.2.dist-info/WHEEL
tesla_api_sdk-1.0.2.dist-info/top_level.txt
tesla_api_sdk-1.0.2.dist-info/RECORD
